pg_cloudconfig/__init__.py
pg_cloudconfig/command.py
pg_cloudconfig/pg_cloudconfig.py
pg_cloudconfig-0.6.dist-info/DESCRIPTION.rst
pg_cloudconfig-0.6.dist-info/METADATA
pg_cloudconfig-0.6.dist-info/RECORD
pg_cloudconfig-0.6.dist-info/WHEEL
pg_cloudconfig-0.6.dist-info/entry_points.txt
pg_cloudconfig-0.6.dist-info/metadata.json
pg_cloudconfig-0.6.dist-info/top_level.txt
pg_cloudconfig-0.6.dist-info/zip-safe
