Metadata-Version: 2.0
Name: pg-cloudconfig
Version: 0.6
Summary: Tool to set optimized defaults for PostgreSQL in virtual environments.
Home-page: https://github.com/credativ/pg_cloudconfig
Author: Alexander Sosna
Author-email: alexander.sosna@credativ.de
License: GPL3
Keywords: postgres postgresql tune tuning cloud
Platform: any
Classifier: Development Status :: 4 - Beta
Classifier: Intended Audience :: System Administrators
Classifier: License :: OSI Approved :: GNU General Public License v3 (GPLv3)
Classifier: Programming Language :: Python :: 3
Requires-Dist: pint
